pubscan/__init__.py
pubscan/__main__.py
pubscan-0.1.4.data/scripts/pubscan
pubscan-0.1.4.dist-info/METADATA
pubscan-0.1.4.dist-info/WHEEL
pubscan-0.1.4.dist-info/RECORD
