Metadata-Version: 2.4
Name: pubscan
Version: 0.1.4
Classifier: Development Status :: 4 - Beta
Classifier: Intended Audience :: Developers
Classifier: License :: OSI Approved :: MIT License
Classifier: Programming Language :: Python :: 3
Classifier: Programming Language :: Python :: 3.8
Classifier: Programming Language :: Python :: 3.9
Classifier: Programming Language :: Python :: 3.10
Classifier: Programming Language :: Python :: 3.11
Classifier: Programming Language :: Python :: 3.12
Classifier: Topic :: Software Development :: Libraries :: Python Modules
Classifier: Topic :: Software Development :: Quality Assurance
Classifier: Programming Language :: Rust
Summary: A tool for analyzing Python module's public API surface area
Author: Your Name <your.email@example.com>
Author-email: Ruff Developers <info@ruff.rs>
License: MIT
Requires-Python: >=3.8
Project-URL: Homepage, https://github.com/astral-sh/ruff
Project-URL: Documentation, https://docs.astral.sh/ruff
Project-URL: Repository, https://github.com/astral-sh/ruff
